odoo/addons/sm_connect/__init__.py
odoo/addons/sm_connect/__manifest__.py
odoo/addons/sm_connect/demo_credentials.json
odoo/addons/sm_connect/models/__init__.py
odoo/addons/sm_connect/models/fleet_vehicle.py
odoo/addons/sm_connect/models/models_sm_carsharing_api_utils.py
odoo/addons/sm_connect/models/models_sm_carsharing_db_utils.py
odoo/addons/sm_connect/models/models_sm_company.py
odoo/addons/sm_connect/models/models_sm_fleetio_api_utils.py
odoo/addons/sm_connect/models/models_sm_res_config_settings.py
odoo/addons/sm_connect/models/models_sm_wordpress_db_utils.py
odoo/addons/sm_connect/security/ir.model.access.csv
odoo/addons/sm_connect/static/src/js/form_controller_confirmation.js
odoo/addons/sm_connect/views/form_view_controller.xml
odoo/addons/sm_connect/views/views_fleetio_car.xml
odoo/addons/sm_connect/views/views_res_config_settings.xml
odoo12_addon_sm_connect-12.0.0.0.24.dist-info/METADATA
odoo12_addon_sm_connect-12.0.0.0.24.dist-info/WHEEL
odoo12_addon_sm_connect-12.0.0.0.24.dist-info/top_level.txt
odoo12_addon_sm_connect-12.0.0.0.24.dist-info/RECORD
